langgraph_a2a_client/__init__.py
langgraph_a2a_client/a2a_client.py
langgraph_a2a_client-0.1.4.dist-info/METADATA
langgraph_a2a_client-0.1.4.dist-info/WHEEL
langgraph_a2a_client-0.1.4.dist-info/licenses/LICENSE
langgraph_a2a_client-0.1.4.dist-info/RECORD
