Metadata-Version: 2.4
Name: langgraph-a2a-client
Version: 0.1.4
Summary: A2A Protocol Client Tool for LangGraph
Project-URL: Repository, https://github.com/5enxia/langgraph-a2a-client
Author-email: 5enxia <5enxia@users.noreply.github.com>
License: MIT License
License-File: LICENSE
Requires-Python: >=3.10
Requires-Dist: a2a-sdk>=0.1.0
Requires-Dist: httpx>=0.27.0
Requires-Dist: langchain-core>=0.2.0
Provides-Extra: examples
Requires-Dist: langchain-openai>=0.3.34; extra == 'examples'
Requires-Dist: langchain>=0.3.27; extra == 'examples'
Requires-Dist: langgraph>=0.6.8; extra == 'examples'
